LICENSE
MANIFEST.in
README.md
requirements.txt
setup.py
torch_utils/__init__.py
torch_utils/__version__.py
torch_utils/accuracy.py
torch_utils/count_parameters.py
torch_utils/initialize.py
torch_utils/meter.py
torch_utils/module_tag.py
torch_utils.egg-info/PKG-INFO
torch_utils.egg-info/SOURCES.txt
torch_utils.egg-info/dependency_links.txt
torch_utils.egg-info/requires.txt
torch_utils.egg-info/top_level.txt