Metadata-Version: 2.1
Name: torch-utils
Version: 0.1.2
Summary: Common Utils for PyTorch
Home-page: https://github.com/FebruaryBreeze/torch-utils
Author: SF-Zhou
Author-email: sfzhou.scut@gmail.com
License: MIT
Keywords: PyTorch Utils
Platform: UNKNOWN
Requires-Python: >=3.6.0
